MANIFEST.in
README.rst
bootstrap.py
buildout.cfg
setup.py
antispoofing/__init__.py
antispoofing.crossdatabase.egg-info/PKG-INFO
antispoofing.crossdatabase.egg-info/SOURCES.txt
antispoofing.crossdatabase.egg-info/dependency_links.txt
antispoofing.crossdatabase.egg-info/entry_points.txt
antispoofing.crossdatabase.egg-info/namespace_packages.txt
antispoofing.crossdatabase.egg-info/requires.txt
antispoofing.crossdatabase.egg-info/top_level.txt
antispoofing/crossdatabase/__init__.py
antispoofing/crossdatabase/helpers/__init__.py
antispoofing/crossdatabase/helpers/utils.py
antispoofing/crossdatabase/script/__init__.py
antispoofing/crossdatabase/script/check_common_errors.py
antispoofing/crossdatabase/script/crossdb_computeQStatistic.py
antispoofing/crossdatabase/script/crossdb_fusion_framework.py
antispoofing/crossdatabase/script/crossdb_result_analysis.py
antispoofing/crossdatabase/script/fusion_faceverif.py