Metadata-Version: 1.0
Name: antispoofing.crossdatabase
Version: 1.0.1
Summary: Antispoofing cross database testing
Home-page: http://pypi.python.org/pypi/antispoofing.crossdatabase
Author: Tiago de Freitas Pereira
Author-email: tiagofrepereira@gmail.com
License: GPLv3
Platform: UNKNOWN
